__main__.py
quicklinks.py
quicklinks_service.py
api/__init__.py
api/actions.py
api/actions_test.py
api/service.py
quicklinks_cli.egg-info/PKG-INFO
quicklinks_cli.egg-info/SOURCES.txt
quicklinks_cli.egg-info/dependency_links.txt
quicklinks_cli.egg-info/entry_points.txt
quicklinks_cli.egg-info/not-zip-safe
quicklinks_cli.egg-info/top_level.txt
quicklinks-0.1.5.post1.dist-info/METADATA
quicklinks-0.1.5.post1.dist-info/WHEEL
quicklinks-0.1.5.post1.dist-info/entry_points.txt
quicklinks-0.1.5.post1.dist-info/top_level.txt
quicklinks-0.1.5.post1.dist-info/RECORD
