Metadata-Version: 2.1
Name: quicklinks
Version: 0.1.5.post1
Summary: Quickly navigate to websites based on shorthands you provide
Home-page: https://github.com/4shub/quicklinks/
Author: Shubham Naik
Author-email: shub@shub.club
License: MIT
Platform: UNKNOWN
Requires-Dist: psutil
